flackup/__init__.py
flackup/cli.py
flackup/convert.py
flackup/fileinfo.py
flackup/musicbrainz.py
flackup-0.7.5.dist-info/licenses/LICENSE
flackup-0.7.5.dist-info/METADATA
flackup-0.7.5.dist-info/WHEEL
flackup-0.7.5.dist-info/entry_points.txt
flackup-0.7.5.dist-info/top_level.txt
flackup-0.7.5.dist-info/RECORD
