Metadata-Version: 2.4
Name: flackup
Version: 0.7.5
Summary: FLAC CD Backup Manager
Author-email: Alexander Dietrich <alexander@dietrich.cx>
License-Expression: GPL-3.0-or-later
Project-URL: Homepage, https://codeberg.org/alxndr42/flackup
Classifier: Operating System :: OS Independent
Classifier: Programming Language :: Python :: 3
Classifier: Topic :: Multimedia :: Sound/Audio :: CD Audio
Classifier: Topic :: Multimedia :: Sound/Audio :: Conversion
Requires-Python: >=3.10
License-File: LICENSE
Requires-Dist: click~=8.2
Requires-Dist: musicbrainzngs~=0.7
Requires-Dist: mutagen~=1.47
Requires-Dist: pillow~=11.3
Dynamic: license-file
